pytorch_forecasting/__init__.py
pytorch_forecasting/data/__init__.py
pytorch_forecasting/data/encoders.py
pytorch_forecasting/data/examples.py
pytorch_forecasting/data/timeseries.py
pytorch_forecasting/metrics.py
pytorch_forecasting/models/__init__.py
pytorch_forecasting/models/base_model.py
pytorch_forecasting/models/baseline.py
pytorch_forecasting/models/basic_rnn/__init__.py
pytorch_forecasting/models/deepar/__init__.py
pytorch_forecasting/models/mlp/__init__.py
pytorch_forecasting/models/mlp/submodules.py
pytorch_forecasting/models/nbeats/__init__.py
pytorch_forecasting/models/nbeats/sub_modules.py
pytorch_forecasting/models/nn/__init__.py
pytorch_forecasting/models/nn/embeddings.py
pytorch_forecasting/models/nn/rnn.py
pytorch_forecasting/models/rnn/__init__.py
pytorch_forecasting/models/temporal_fusion_transformer/__init__.py
pytorch_forecasting/models/temporal_fusion_transformer/sub_modules.py
pytorch_forecasting/models/temporal_fusion_transformer/tuning.py
pytorch_forecasting/optim.py
pytorch_forecasting/utils.py
pytorch_forecasting_unofficial_hotfix-0.9.3.dist-info/LICENSE
pytorch_forecasting_unofficial_hotfix-0.9.3.dist-info/WHEEL
pytorch_forecasting_unofficial_hotfix-0.9.3.dist-info/METADATA
pytorch_forecasting_unofficial_hotfix-0.9.3.dist-info/RECORD
