Metadata-Version: 2.1
Name: pytorch-forecasting-unofficial-hotfix
Version: 0.9.3
Summary: Forecasting timeseries with PyTorch - dataloaders, normalizers, metrics and models
Home-page: https://pytorch-forecasting.readthedocs.io
Author: Jan Beitner
Requires-Python: >=3.7.1,<4.0.0
Classifier: Intended Audience :: Developers
Classifier: Intended Audience :: Science/Research
Classifier: License :: OSI Approved :: MIT License
Classifier: Programming Language :: Python :: 3
Classifier: Programming Language :: Python :: 3.10
Classifier: Programming Language :: Python :: 3.6
Classifier: Programming Language :: Python :: 3.7
Classifier: Programming Language :: Python :: 3.8
Classifier: Programming Language :: Python :: 3.9
Classifier: Topic :: Scientific/Engineering
Classifier: Topic :: Scientific/Engineering :: Artificial Intelligence
Classifier: Topic :: Scientific/Engineering :: Mathematics
Classifier: Topic :: Software Development
Classifier: Topic :: Software Development :: Libraries
Classifier: Topic :: Software Development :: Libraries :: Python Modules
Provides-Extra: github-actions
Requires-Dist: matplotlib
Requires-Dist: optuna (>=2.3.0,<3.0.0)
Requires-Dist: pandas (>=1.3.0,<2.0.0)
Requires-Dist: pytest-github-actions-annotate-failures; extra == "github-actions"
Requires-Dist: pytorch-lightning (>=1.2.4,<2.0.0)
Requires-Dist: scikit-learn (>=0.24,<1.1)
Requires-Dist: scipy
Requires-Dist: statsmodels
Requires-Dist: torch (>=1.7,<2.0)
Project-URL: Documentation, https://pytorch-forecasting.readthedocs.io
Project-URL: Repository, https://github.com/jdb78/pytorch-forecasting
